dotgov/__init__.py
dotgov/constants.py
dotgov/py.typed
dotgov/socrata.py
dotgov-0.1.2.dist-info/licenses/LICENSE
dotgov-0.1.2.dist-info/WHEEL
dotgov-0.1.2.dist-info/METADATA
dotgov-0.1.2.dist-info/RECORD
